spanish_tools/__init__.py
spanish_tools/cleaning.py
spanish_tools/core.py
spanish_tools/normalization.py
spanish_tools-0.1.1.dist-info/licenses/LICENSE
spanish_tools-0.1.1.dist-info/METADATA
spanish_tools-0.1.1.dist-info/WHEEL
spanish_tools-0.1.1.dist-info/top_level.txt
spanish_tools-0.1.1.dist-info/RECORD
