Metadata-Version: 2.4
Name: spanish_tools
Version: 0.1.1
Summary: Intelligent data processing tools for Spanish datasets (encoding, dates, numbers).
License: MIT License
Project-URL: Homepage, https://github.com/AleLoredo/spanish-tools
Keywords: pandas,spanish,data-cleaning,csv,normalization
Classifier: Programming Language :: Python :: 3
Classifier: License :: OSI Approved :: MIT License
Classifier: Operating System :: OS Independent
Classifier: Topic :: Scientific/Engineering :: Information Analysis
Classifier: Natural Language :: Spanish
Requires-Python: >=3.7
License-File: LICENSE
Requires-Dist: pandas>=1.0.0
Requires-Dist: openpyxl>=3.0.0
Requires-Dist: xlrd>=2.0.0
Requires-Dist: odfpy>=1.4.0
Requires-Dist: lxml>=4.0.0
Dynamic: license-file
